{
  "name": "react-redux-realworld-example-app",
  "repoUrl": "https://github.com/gothinkster/react-redux-realworld-example-app",
  "lane": "class-react-to-hooks",
  "createdAt": "2026-07-07T05:00:48.724Z",
  "stages": [
    {
      "stage": "select",
      "status": "passed",
      "finishedAt": "2026-07-07T05:00:48.728Z",
      "notes": "cloned at ee72eba, MIT, archived upstream; nested .git stripped, SHA recorded in target-rationale.md"
    },
    {
      "stage": "analyze",
      "status": "passed",
      "finishedAt": "2026-07-07T05:04:59.902Z",
      "executor": "fable",
      "notes": "migration-plan.md: 7 risks, M0-M7 sequence, 4-layer characterization plan"
    },
    {
      "stage": "testgen",
      "status": "passed",
      "finishedAt": "2026-07-07T05:22:11.111Z",
      "executor": "sonnet",
      "notes": "18 files / 157 tests: reducers(83) middleware(12) agent(28) flows(26) + harness"
    },
    {
      "stage": "migrate",
      "status": "pending"
    },
    {
      "stage": "review",
      "status": "pending"
    },
    {
      "stage": "document",
      "status": "pending"
    },
    {
      "stage": "validate",
      "status": "pending"
    }
  ],
  "decisions": [
    {
      "ts": "2026-07-07T05:00:48.729Z",
      "stage": "select",
      "rationale": "Chose archived MIT realworld app over larger GPL/unlicensed candidates; 2340 LOC slightly under rough floor — flagged in target-rationale.md"
    },
    {
      "ts": "2026-07-07T05:04:59.905Z",
      "stage": "analyze",
      "rationale": "React 17 (not 18): createRoot auto-batching would change observable update timing — out of migration scope"
    },
    {
      "ts": "2026-07-07T05:04:59.906Z",
      "stage": "analyze",
      "rationale": "react-router-dom 5.3.4 (not 6): v4 Switch/Route/exact semantics carry over identically; v6 rewrite listed as follow-up"
    },
    {
      "ts": "2026-07-07T05:04:59.907Z",
      "stage": "analyze",
      "rationale": "marked stays pinned 0.3.6: sanitize:true removed in modern marked, exact escaping not reproducible — CVEs flagged for review report"
    },
    {
      "ts": "2026-07-07T05:04:59.909Z",
      "stage": "analyze",
      "rationale": "superagent kept, superagent-promise dropped: superagent>=3 natively thenable with identical resolve/reject shapes; HTTP lib swap is out of lane"
    },
    {
      "ts": "2026-07-07T05:04:59.910Z",
      "stage": "analyze",
      "rationale": "Known upstream bugs preserved, not fixed (pagination page-size mismatch, jwt '' on logout, undefined controlled inputs, DELETE_COMMENT null assumption)"
    },
    {
      "ts": "2026-07-07T05:22:11.113Z",
      "stage": "testgen",
      "rationale": "Characterized 7 as-is behaviors incl. DELETE_COMMENT throw on undefined comments, logout jwt=''  not removeItem, settings ASYNC_START no subtype gate, unreachable PROFILE_FAVORITES_* action types, omitSlug slug:undefined key, marked sanitize escaping, unguarded favorite dispatch"
    },
    {
      "ts": "2026-07-07T07:48:03.518Z",
      "stage": "migrate",
      "rationale": "M0: .js→.jsx renames so stock Vite handles JSX; extensionless imports unchanged"
    },
    {
      "ts": "2026-07-07T07:48:03.520Z",
      "stage": "migrate",
      "rationale": "M0: dropped write-only state.router slice with react-router-redux; redirect now history.push in App"
    }
  ],
  "testGates": [
    {
      "ts": "2026-07-07T05:22:11.108Z",
      "stage": "testgen",
      "command": "TARGET=original npx vitest run",
      "cwd": "runs/react-redux-realworld-example-app/characterization",
      "ok": true,
      "summary": "Tests  157 passed (157) — golden master green on ORIGINAL"
    },
    {
      "ts": "2026-07-07T07:48:03.514Z",
      "stage": "migrate",
      "command": "TARGET=migrated npx vitest run",
      "cwd": "runs/react-redux-realworld-example-app/characterization",
      "ok": true,
      "summary": "M0 toolchain: Tests 157 passed (157) + vite build clean"
    }
  ]
}
